{"v":"4.8.0","meta":{"g":"LottieFiles AE ","a":"","k":"","d":"","tc":""},"fr":24,"ip":0,"op":31,"w":750,"h":1624,"nm":"컴포지션 1","ddd":0,"assets":[{"id":"image_0","w":750,"h":1624,"u":"images/","p":"dark_0.png","e":0},{"id":"image_1","w":750,"h":1624,"u":"images/","p":"dark_1.png","e":0},{"id":"image_2","w":750,"h":1624,"u":"images/","p":"dark_2.png","e":0},{"id":"image_3","w":750,"h":1624,"u":"images/","p":"dark_3.png","e":0},{"id":"image_4","w":750,"h":1624,"u":"images/","p":"dark_4.png","e":0},{"id":"image_5","w":750,"h":1624,"u":"images/","p":"dark_5.png","e":0},{"id":"image_6","w":750,"h":1624,"u":"images/","p":"dark_6.png","e":0},{"id":"image_7","w":750,"h":1624,"u":"images/","p":"dark_7.png","e":0},{"id":"image_8","w":750,"h":1624,"u":"images/","p":"dark_8.png","e":0},{"id":"image_9","w":750,"h":1624,"u":"images/","p":"dark_9.png","e":0},{"id":"image_10","w":750,"h":1624,"u":"images/","p":"dark_10.png","e":0},{"id":"image_11","w":750,"h":1624,"u":"images/","p":"dark_11.png","e":0},{"id":"image_12","w":750,"h":1624,"u":"images/","p":"dark_12.png","e":0},{"id":"image_13","w":750,"h":1624,"u":"images/","p":"dark_13.png","e":0},{"id":"image_14","w":750,"h":1624,"u":"images/","p":"dark_14.png","e":0},{"id":"image_15","w":750,"h":1624,"u":"images/","p":"dark_15.png","e":0},{"id":"image_16","w":750,"h":1624,"u":"images/","p":"dark_16.png","e":0},{"id":"image_17","w":750,"h":1624,"u":"images/","p":"dark_17.png","e":0},{"id":"image_18","w":750,"h":1624,"u":"images/","p":"dark_18.png","e":0},{"id":"image_19","w":750,"h":1624,"u":"images/","p":"dark_19.png","e":0},{"id":"image_20","w":750,"h":1624,"u":"images/","p":"dark_20.png","e":0},{"id":"image_21","w":750,"h":1624,"u":"images/","p":"dark_21.png","e":0},{"id":"image_22","w":750,"h":1624,"u":"images/","p":"dark_22.png","e":0},{"id":"image_23","w":750,"h":1624,"u":"images/","p":"dark_23.png","e":0},{"id":"image_24","w":750,"h":1624,"u":"images/","p":"dark_24.png","e":0},{"id":"image_25","w":750,"h":1624,"u":"images/","p":"dark_25.png","e":0},{"id":"image_26","w":750,"h":1624,"u":"images/","p":"dark_26.png","e":0},{"id":"image_27","w":750,"h":1624,"u":"images/","p":"dark_27.png","e":0},{"id":"image_28","w":750,"h":1624,"u":"images/","p":"dark_28.png","e":0},{"id":"image_29","w":750,"h":1624,"u":"images/","p":"dark_29.png","e":0},{"id":"image_30","w":750,"h":1624,"u":"images/","p":"dark_30.png","e":0}],"layers":[{"ddd":0,"ind":2,"ty":2,"nm":"sui_dark_00000.png","cl":"png","refId":"image_0","sr":1,"ks":{"o":{"a":0,"k":100,"ix":11},"r":{"a":0,"k":0,"ix":10},"p":{"a":0,"k":[375,812,0],"ix":2},"a":{"a":0,"k":[375,812,0],"ix":1},"s":{"a":0,"k":[100,100,100],"ix":6}},"ao":0,"ip":0,"op":1,"st":0,"bm":0},{"ddd":0,"ind":3,"ty":2,"nm":"sui_dark_00001.png","cl":"png","refId":"image_1","sr":1,"ks":{"o":{"a":0,"k":100,"ix":11},"r":{"a":0,"k":0,"ix":10},"p":{"a":0,"k":[375,812,0],"ix":2},"a":{"a":0,"k":[375,812,0],"ix":1},"s":{"a":0,"k":[100,100,100],"ix":6}},"ao":0,"ip":1,"op":2,"st":1,"bm":0},{"ddd":0,"ind":4,"ty":2,"nm":"sui_dark_00002.png","cl":"png","refId":"image_2","sr":1,"ks":{"o":{"a":0,"k":100,"ix":11},"r":{"a":0,"k":0,"ix":10},"p":{"a":0,"k":[375,812,0],"ix":2},"a":{"a":0,"k":[375,812,0],"ix":1},"s":{"a":0,"k":[100,100,100],"ix":6}},"ao":0,"ip":2,"op":3,"st":2,"bm":0},{"ddd":0,"ind":5,"ty":2,"nm":"sui_dark_00003.png","cl":"png","refId":"image_3","sr":1,"ks":{"o":{"a":0,"k":100,"ix":11},"r":{"a":0,"k":0,"ix":10},"p":{"a":0,"k":[375,812,0],"ix":2},"a":{"a":0,"k":[375,812,0],"ix":1},"s":{"a":0,"k":[100,100,100],"ix":6}},"ao":0,"ip":3,"op":4,"st":3,"bm":0},{"ddd":0,"ind":6,"ty":2,"nm":"sui_dark_00004.png","cl":"png","refId":"image_4","sr":1,"ks":{"o":{"a":0,"k":100,"ix":11},"r":{"a":0,"k":0,"ix":10},"p":{"a":0,"k":[375,812,0],"ix":2},"a":{"a":0,"k":[375,812,0],"ix":1},"s":{"a":0,"k":[100,100,100],"ix":6}},"ao":0,"ip":4,"op":5,"st":4,"bm":0},{"ddd":0,"ind":7,"ty":2,"nm":"sui_dark_00005.png","cl":"png","refId":"image_5","sr":1,"ks":{"o":{"a":0,"k":100,"ix":11},"r":{"a":0,"k":0,"ix":10},"p":{"a":0,"k":[375,812,0],"ix":2},"a":{"a":0,"k":[375,812,0],"ix":1},"s":{"a":0,"k":[100,100,100],"ix":6}},"ao":0,"ip":5,"op":6,"st":5,"bm":0},{"ddd":0,"ind":8,"ty":2,"nm":"sui_dark_00006.png","cl":"png","refId":"image_6","sr":1,"ks":{"o":{"a":0,"k":100,"ix":11},"r":{"a":0,"k":0,"ix":10},"p":{"a":0,"k":[375,812,0],"ix":2},"a":{"a":0,"k":[375,812,0],"ix":1},"s":{"a":0,"k":[100,100,100],"ix":6}},"ao":0,"ip":6,"op":7,"st":6,"bm":0},{"ddd":0,"ind":9,"ty":2,"nm":"sui_dark_00007.png","cl":"png","refId":"image_7","sr":1,"ks":{"o":{"a":0,"k":100,"ix":11},"r":{"a":0,"k":0,"ix":10},"p":{"a":0,"k":[375,812,0],"ix":2},"a":{"a":0,"k":[375,812,0],"ix":1},"s":{"a":0,"k":[100,100,100],"ix":6}},"ao":0,"ip":7,"op":8,"st":7,"bm":0},{"ddd":0,"ind":10,"ty":2,"nm":"sui_dark_00008.png","cl":"png","refId":"image_8","sr":1,"ks":{"o":{"a":0,"k":100,"ix":11},"r":{"a":0,"k":0,"ix":10},"p":{"a":0,"k":[375,812,0],"ix":2},"a":{"a":0,"k":[375,812,0],"ix":1},"s":{"a":0,"k":[100,100,100],"ix":6}},"ao":0,"ip":8,"op":9,"st":8,"bm":0},{"ddd":0,"ind":11,"ty":2,"nm":"sui_dark_00009.png","cl":"png","refId":"image_9","sr":1,"ks":{"o":{"a":0,"k":100,"ix":11},"r":{"a":0,"k":0,"ix":10},"p":{"a":0,"k":[375,812,0],"ix":2},"a":{"a":0,"k":[375,812,0],"ix":1},"s":{"a":0,"k":[100,100,100],"ix":6}},"ao":0,"ip":9,"op":10,"st":9,"bm":0},{"ddd":0,"ind":12,"ty":2,"nm":"sui_dark_00010.png","cl":"png","refId":"image_10","sr":1,"ks":{"o":{"a":0,"k":100,"ix":11},"r":{"a":0,"k":0,"ix":10},"p":{"a":0,"k":[375,812,0],"ix":2},"a":{"a":0,"k":[375,812,0],"ix":1},"s":{"a":0,"k":[100,100,100],"ix":6}},"ao":0,"ip":10,"op":11,"st":10,"bm":0},{"ddd":0,"ind":13,"ty":2,"nm":"sui_dark_00011.png","cl":"png","refId":"image_11","sr":1,"ks":{"o":{"a":0,"k":100,"ix":11},"r":{"a":0,"k":0,"ix":10},"p":{"a":0,"k":[375,812,0],"ix":2},"a":{"a":0,"k":[375,812,0],"ix":1},"s":{"a":0,"k":[100,100,100],"ix":6}},"ao":0,"ip":11,"op":12,"st":11,"bm":0},{"ddd":0,"ind":14,"ty":2,"nm":"sui_dark_00012.png","cl":"png","refId":"image_12","sr":1,"ks":{"o":{"a":0,"k":100,"ix":11},"r":{"a":0,"k":0,"ix":10},"p":{"a":0,"k":[375,812,0],"ix":2},"a":{"a":0,"k":[375,812,0],"ix":1},"s":{"a":0,"k":[100,100,100],"ix":6}},"ao":0,"ip":12,"op":13,"st":12,"bm":0},{"ddd":0,"ind":15,"ty":2,"nm":"sui_dark_00013.png","cl":"png","refId":"image_13","sr":1,"ks":{"o":{"a":0,"k":100,"ix":11},"r":{"a":0,"k":0,"ix":10},"p":{"a":0,"k":[375,812,0],"ix":2},"a":{"a":0,"k":[375,812,0],"ix":1},"s":{"a":0,"k":[100,100,100],"ix":6}},"ao":0,"ip":13,"op":14,"st":13,"bm":0},{"ddd":0,"ind":16,"ty":2,"nm":"sui_dark_00014.png","cl":"png","refId":"image_14","sr":1,"ks":{"o":{"a":0,"k":100,"ix":11},"r":{"a":0,"k":0,"ix":10},"p":{"a":0,"k":[375,812,0],"ix":2},"a":{"a":0,"k":[375,812,0],"ix":1},"s":{"a":0,"k":[100,100,100],"ix":6}},"ao":0,"ip":14,"op":15,"st":14,"bm":0},{"ddd":0,"ind":17,"ty":2,"nm":"sui_dark_00015.png","cl":"png","refId":"image_15","sr":1,"ks":{"o":{"a":0,"k":100,"ix":11},"r":{"a":0,"k":0,"ix":10},"p":{"a":0,"k":[375,812,0],"ix":2},"a":{"a":0,"k":[375,812,0],"ix":1},"s":{"a":0,"k":[100,100,100],"ix":6}},"ao":0,"ip":15,"op":16,"st":15,"bm":0},{"ddd":0,"ind":18,"ty":2,"nm":"sui_dark_00016.png","cl":"png","refId":"image_16","sr":1,"ks":{"o":{"a":0,"k":100,"ix":11},"r":{"a":0,"k":0,"ix":10},"p":{"a":0,"k":[375,812,0],"ix":2},"a":{"a":0,"k":[375,812,0],"ix":1},"s":{"a":0,"k":[100,100,100],"ix":6}},"ao":0,"ip":16,"op":17,"st":16,"bm":0},{"ddd":0,"ind":19,"ty":2,"nm":"sui_dark_00017.png","cl":"png","refId":"image_17","sr":1,"ks":{"o":{"a":0,"k":100,"ix":11},"r":{"a":0,"k":0,"ix":10},"p":{"a":0,"k":[375,812,0],"ix":2},"a":{"a":0,"k":[375,812,0],"ix":1},"s":{"a":0,"k":[100,100,100],"ix":6}},"ao":0,"ip":17,"op":18,"st":17,"bm":0},{"ddd":0,"ind":20,"ty":2,"nm":"sui_dark_00018.png","cl":"png","refId":"image_18","sr":1,"ks":{"o":{"a":0,"k":100,"ix":11},"r":{"a":0,"k":0,"ix":10},"p":{"a":0,"k":[375,812,0],"ix":2},"a":{"a":0,"k":[375,812,0],"ix":1},"s":{"a":0,"k":[100,100,100],"ix":6}},"ao":0,"ip":18,"op":19,"st":18,"bm":0},{"ddd":0,"ind":21,"ty":2,"nm":"sui_dark_00019.png","cl":"png","refId":"image_19","sr":1,"ks":{"o":{"a":0,"k":100,"ix":11},"r":{"a":0,"k":0,"ix":10},"p":{"a":0,"k":[375,812,0],"ix":2},"a":{"a":0,"k":[375,812,0],"ix":1},"s":{"a":0,"k":[100,100,100],"ix":6}},"ao":0,"ip":19,"op":20,"st":19,"bm":0},{"ddd":0,"ind":22,"ty":2,"nm":"sui_dark_00020.png","cl":"png","refId":"image_20","sr":1,"ks":{"o":{"a":0,"k":100,"ix":11},"r":{"a":0,"k":0,"ix":10},"p":{"a":0,"k":[375,812,0],"ix":2},"a":{"a":0,"k":[375,812,0],"ix":1},"s":{"a":0,"k":[100,100,100],"ix":6}},"ao":0,"ip":20,"op":21,"st":20,"bm":0},{"ddd":0,"ind":23,"ty":2,"nm":"sui_dark_00021.png","cl":"png","refId":"image_21","sr":1,"ks":{"o":{"a":0,"k":100,"ix":11},"r":{"a":0,"k":0,"ix":10},"p":{"a":0,"k":[375,812,0],"ix":2},"a":{"a":0,"k":[375,812,0],"ix":1},"s":{"a":0,"k":[100,100,100],"ix":6}},"ao":0,"ip":21,"op":22,"st":21,"bm":0},{"ddd":0,"ind":24,"ty":2,"nm":"sui_dark_00022.png","cl":"png","refId":"image_22","sr":1,"ks":{"o":{"a":0,"k":100,"ix":11},"r":{"a":0,"k":0,"ix":10},"p":{"a":0,"k":[375,812,0],"ix":2},"a":{"a":0,"k":[375,812,0],"ix":1},"s":{"a":0,"k":[100,100,100],"ix":6}},"ao":0,"ip":22,"op":23,"st":22,"bm":0},{"ddd":0,"ind":25,"ty":2,"nm":"sui_dark_00023.png","cl":"png","refId":"image_23","sr":1,"ks":{"o":{"a":0,"k":100,"ix":11},"r":{"a":0,"k":0,"ix":10},"p":{"a":0,"k":[375,812,0],"ix":2},"a":{"a":0,"k":[375,812,0],"ix":1},"s":{"a":0,"k":[100,100,100],"ix":6}},"ao":0,"ip":23,"op":24,"st":23,"bm":0},{"ddd":0,"ind":26,"ty":2,"nm":"sui_dark_00024.png","cl":"png","refId":"image_24","sr":1,"ks":{"o":{"a":0,"k":100,"ix":11},"r":{"a":0,"k":0,"ix":10},"p":{"a":0,"k":[375,812,0],"ix":2},"a":{"a":0,"k":[375,812,0],"ix":1},"s":{"a":0,"k":[100,100,100],"ix":6}},"ao":0,"ip":24,"op":25,"st":24,"bm":0},{"ddd":0,"ind":27,"ty":2,"nm":"sui_dark_00025.png","cl":"png","refId":"image_25","sr":1,"ks":{"o":{"a":0,"k":100,"ix":11},"r":{"a":0,"k":0,"ix":10},"p":{"a":0,"k":[375,812,0],"ix":2},"a":{"a":0,"k":[375,812,0],"ix":1},"s":{"a":0,"k":[100,100,100],"ix":6}},"ao":0,"ip":25,"op":26,"st":25,"bm":0},{"ddd":0,"ind":28,"ty":2,"nm":"sui_dark_00026.png","cl":"png","refId":"image_26","sr":1,"ks":{"o":{"a":0,"k":100,"ix":11},"r":{"a":0,"k":0,"ix":10},"p":{"a":0,"k":[375,812,0],"ix":2},"a":{"a":0,"k":[375,812,0],"ix":1},"s":{"a":0,"k":[100,100,100],"ix":6}},"ao":0,"ip":26,"op":27,"st":26,"bm":0},{"ddd":0,"ind":29,"ty":2,"nm":"sui_dark_00027.png","cl":"png","refId":"image_27","sr":1,"ks":{"o":{"a":0,"k":100,"ix":11},"r":{"a":0,"k":0,"ix":10},"p":{"a":0,"k":[375,812,0],"ix":2},"a":{"a":0,"k":[375,812,0],"ix":1},"s":{"a":0,"k":[100,100,100],"ix":6}},"ao":0,"ip":27,"op":28,"st":27,"bm":0},{"ddd":0,"ind":30,"ty":2,"nm":"sui_dark_00028.png","cl":"png","refId":"image_28","sr":1,"ks":{"o":{"a":0,"k":100,"ix":11},"r":{"a":0,"k":0,"ix":10},"p":{"a":0,"k":[375,812,0],"ix":2},"a":{"a":0,"k":[375,812,0],"ix":1},"s":{"a":0,"k":[100,100,100],"ix":6}},"ao":0,"ip":28,"op":29,"st":28,"bm":0},{"ddd":0,"ind":31,"ty":2,"nm":"sui_dark_00029.png","cl":"png","refId":"image_29","sr":1,"ks":{"o":{"a":0,"k":100,"ix":11},"r":{"a":0,"k":0,"ix":10},"p":{"a":0,"k":[375,812,0],"ix":2},"a":{"a":0,"k":[375,812,0],"ix":1},"s":{"a":0,"k":[100,100,100],"ix":6}},"ao":0,"ip":29,"op":30,"st":29,"bm":0},{"ddd":0,"ind":32,"ty":2,"nm":"sui_dark_00030.png","cl":"png","refId":"image_30","sr":1,"ks":{"o":{"a":0,"k":100,"ix":11},"r":{"a":0,"k":0,"ix":10},"p":{"a":0,"k":[375,812,0],"ix":2},"a":{"a":0,"k":[375,812,0],"ix":1},"s":{"a":0,"k":[100,100,100],"ix":6}},"ao":0,"ip":30,"op":31,"st":30,"bm":0}],"markers":[]}
